cloudrunner-1.3.2_3.data/scripts/cloudrunner-autocomplete
cloudrunner-1.3.2_3.dist-info/DESCRIPTION.rst
cloudrunner-1.3.2_3.dist-info/WHEEL
cloudrunner-1.3.2_3.dist-info/METADATA
cloudrunner-1.3.2_3.dist-info/top_level.txt
cloudrunner-1.3.2_3.dist-info/metadata.json
cloudrunner-1.3.2_3.dist-info/RECORD
cloudrunner-1.3.2_3.dist-info/entry_points.txt
cloudrunner/version.py
cloudrunner/__init__.py
cloudrunner/plugins/args_provider.py
cloudrunner/plugins/__init__.py
cloudrunner/plugins/state/base.py
cloudrunner/plugins/state/__init__.py
cloudrunner/plugins/state/functions.py
cloudrunner/plugins/transport/node_transport.py
cloudrunner/plugins/transport/zmq_node_transport.py
cloudrunner/plugins/transport/rest_transport.py
cloudrunner/plugins/transport/base.py
cloudrunner/plugins/transport/zmq_transport.py
cloudrunner/plugins/transport/__init__.py
cloudrunner/node/agent.py
cloudrunner/node/__init__.py
cloudrunner/node/matcher.py
cloudrunner/core/statemanager.py
cloudrunner/core/exceptions.py
cloudrunner/core/process.py
cloudrunner/core/parser.py
cloudrunner/core/__init__.py
cloudrunner/core/message.py
cloudrunner/core/tests/test_state.py
cloudrunner/core/tests/test_process.py
cloudrunner/core/tests/test_message.py
cloudrunner/core/tests/__init__.py
cloudrunner/core/tests/test_parser.py
cloudrunner/core/platform/__init__.py
cloudrunner/core/platform/nt.py
cloudrunner/core/platform/nix.py
cloudrunner/core/platform/tests/test_nix.py
cloudrunner/core/platform/tests/__init__.py
cloudrunner/core/platform/tests/test_nt.py
cloudrunner/api/client.py
cloudrunner/api/base.py
cloudrunner/api/__init__.py
cloudrunner/api/nodes.py
cloudrunner/api/library.py
cloudrunner/api/logs.py
cloudrunner/api/exceptions/__init__.py
cloudrunner/util/cert_store.py
cloudrunner/util/decorators.py
cloudrunner/util/crypto.py
cloudrunner/util/string.py
cloudrunner/util/psutil_wrapper.py
cloudrunner/util/shell.py
cloudrunner/util/loader.py
cloudrunner/util/http.py
cloudrunner/util/logconfig.py
cloudrunner/util/daemon.py
cloudrunner/util/validator.py
cloudrunner/util/__init__.py
cloudrunner/util/nt.py
cloudrunner/util/aes_crypto.py
cloudrunner/util/tlszmq.py
cloudrunner/util/config.py
cloudrunner/util/net.py
cloudrunner/util/nix.py
