Metadata-Version: 2.0
Name: cloudrunner
Version: 1.3.2-3
Summary: Script execution engine for cloud environments.
Home-page: http://www.cloudrunner.io/
Author: CloudRunner.IO Dev Team
Author-email: dev@cloudrunner.io
License: Apache
Platform: UNKNOWN
Classifier: Development Status :: 4 - Beta
Classifier: Environment :: Console
Classifier: Intended Audience :: Developers
Classifier: Intended Audience :: System Administrators
Classifier: License :: OSI Approved :: Apache Software License
Classifier: Operating System :: OS Independent
Classifier: Programming Language :: Python
Classifier: Programming Language :: Python :: 2
Classifier: Programming Language :: Python :: 2.6
Classifier: Programming Language :: Python :: 2.7
Classifier: Topic :: Internet :: WWW/HTTP
Classifier: Topic :: Software Development :: Libraries :: Application Frameworks
Classifier: Topic :: Software Development :: Libraries :: Python Modules
Requires-Dist: pyzmq
Requires-Dist: M2Crypto
Requires-Dist: httplib2
Requires-Dist: msgpack-python (>=0.4)
Requires-Dist: psutil
Requires-Dist: ipy
Requires-Dist: requests
